condenseseq/__init__.py
condenseseq/__main__.py
expandseq/__init__.py
expandseq/__main__.py
expandSeq-4.0.0.dist-info/LICENSE
expandSeq-4.0.0.dist-info/METADATA
expandSeq-4.0.0.dist-info/WHEEL
expandSeq-4.0.0.dist-info/entry_points.txt
expandSeq-4.0.0.dist-info/top_level.txt
expandSeq-4.0.0.dist-info/RECORD
