Metadata-Version: 2.2
Name: expandSeq
Version: 4.0.0
Summary: Command line utils to expose functionality of seqLister python library.
Home-page: https://github.com/jrowellfx/expandSeq
Author: James Philip Rowell
Author-email: james@alpha-eleven.com
Classifier: Programming Language :: Python :: 3
Classifier: License :: OSI Approved :: BSD License
Classifier: Operating System :: POSIX
Classifier: Operating System :: Unix
Classifier: Operating System :: MacOS
Classifier: Development Status :: 5 - Production/Stable
Requires-Python: >=3.6, <4
License-File: LICENSE
Requires-Dist: seqLister>=1.1.0
Dynamic: author
Dynamic: author-email
Dynamic: classifier
Dynamic: description
Dynamic: description-content-type
Dynamic: home-page
Dynamic: requires-dist
Dynamic: requires-python
Dynamic: summary
